flask_container_scaffold/__init__.py
flask_container_scaffold/app_configurator.py
flask_container_scaffold/app_scaffold.py
flask_container_scaffold/base.py
flask_container_scaffold/base_scaffold.py
flask_container_scaffold/celery_scaffold.py
flask_container_scaffold/logging.py
flask_container_scaffold/network.py
flask_container_scaffold/util.py
flask_container_scaffold-0.3.1.dist-info/LICENSE
flask_container_scaffold-0.3.1.dist-info/METADATA
flask_container_scaffold-0.3.1.dist-info/WHEEL
flask_container_scaffold-0.3.1.dist-info/top_level.txt
flask_container_scaffold-0.3.1.dist-info/RECORD
