Metadata-Version: 2.1
Name: flask-container-scaffold
Version: 0.3.1
Summary: Configuration layer to aid in deployment of Flask apps
Home-page: https://github.com/release-depot/flask-container-scaffold
Author: Jason Guiditta
Author-email: jason.guiditta@gmail.com
License: MIT
Project-URL: Bug Tracker, https://github.com/release-depot/flask-container-scaffold/issues
Classifier: Development Status :: 3 - Alpha
Classifier: Environment :: Web Environment
Classifier: Intended Audience :: Developers
Classifier: License :: OSI Approved :: MIT License
Classifier: Programming Language :: Python :: 3
Classifier: Operating System :: OS Independent
License-File: LICENSE
Requires-Dist: flask
Requires-Dist: pydantic
Requires-Dist: toolchest
Provides-Extra: celery
Requires-Dist: celery ; extra == 'celery'
Provides-Extra: devbase
Requires-Dist: tox ; extra == 'devbase'
Provides-Extra: dist
Requires-Dist: build ; extra == 'dist'
Requires-Dist: setuptools-scm ; extra == 'dist'
Requires-Dist: twine ; extra == 'dist'
Provides-Extra: docs
Requires-Dist: sphinx ; extra == 'docs'
Requires-Dist: sphinx-autobuild ; extra == 'docs'
Requires-Dist: sphinx-rtd-theme ; extra == 'docs'
Requires-Dist: myst-parser ; extra == 'docs'
Provides-Extra: test
Requires-Dist: flake8 ; extra == 'test'
Requires-Dist: pytest ; extra == 'test'
Requires-Dist: pytest-cov ; extra == 'test'
